tf2jax/__init__.py
tf2jax/py.typed
tf2jax/tf2jax_test.py
tf2jax/_src/__init__.py
tf2jax/_src/config.py
tf2jax/_src/linalg_ops_test.py
tf2jax/_src/numpy_compat.py
tf2jax/_src/numpy_compat_test.py
tf2jax/_src/ops.py
tf2jax/_src/ops_test.py
tf2jax/_src/roundtrip_test.py
tf2jax/_src/sharding_test.py
tf2jax/_src/test_util.py
tf2jax/_src/tf2jax.py
tf2jax/_src/tf2jax_test.py
tf2jax/_src/utils.py
tf2jax/_src/xla_utils.py
tf2jax/experimental/__init__.py
tf2jax/experimental/mhlo.py
tf2jax/experimental/mhlo_test.py
tf2jax/experimental/ops.py
tf2jax/test_data/custom_gradient_cubed/fingerprint.pb
tf2jax/test_data/custom_gradient_cubed/saved_model.pb
tf2jax/test_data/custom_gradient_cubed/variables/variables.data-00000-of-00001
tf2jax/test_data/custom_gradient_cubed/variables/variables.index
tf2jax-0.3.8.dist-info/licenses/LICENSE
tf2jax-0.3.8.dist-info/METADATA
tf2jax-0.3.8.dist-info/WHEEL
tf2jax-0.3.8.dist-info/top_level.txt
tf2jax-0.3.8.dist-info/RECORD
