Metadata-Version: 2.4
Name: tf2jax
Version: 0.3.8
Summary: TF2JAX: Convert TensorFlow to JAX
Home-page: https://github.com/deepmind/tf2jax
Author: DeepMind
Author-email: tf2jax-dev@google.com
License: Apache 2.0
Keywords: jax tensorflow conversion translate
Classifier: Development Status :: 4 - Beta
Classifier: Intended Audience :: Developers
Classifier: Intended Audience :: Education
Classifier: Intended Audience :: Science/Research
Classifier: License :: OSI Approved :: Apache Software License
Classifier: Operating System :: OS Independent
Classifier: Programming Language :: Python :: 3.11
Classifier: Programming Language :: Python :: 3.12
Classifier: Topic :: Scientific/Engineering :: Artificial Intelligence
Classifier: Topic :: Scientific/Engineering :: Mathematics
Classifier: Topic :: Software Development :: Libraries :: Python Modules
Classifier: Topic :: Software Development :: Libraries
Requires-Python: >=3.11
License-File: LICENSE
Requires-Dist: absl-py
Requires-Dist: dm-tree>=0.1.5
Requires-Dist: jax>=0.7.1
Requires-Dist: jaxlib>=0.7.1
Requires-Dist: numpy>=1.23.0
Requires-Dist: tensorflow>=2.20.0; sys_platform != "darwin" or platform_machine != "arm64"
Requires-Dist: tensorflow-macos>=2.20.0; sys_platform == "darwin" and platform_machine == "arm64"
Dynamic: author
Dynamic: author-email
Dynamic: classifier
Dynamic: description
Dynamic: description-content-type
Dynamic: home-page
Dynamic: keywords
Dynamic: license
Dynamic: license-file
Dynamic: requires-dist
Dynamic: requires-python
Dynamic: summary
